Metadata-Version: 2.1
Name: odoo11-addon-auth-signup-verify-email
Version: 11.0.1.0.1
Summary: Force uninvited users to use a good email for signup
Home-page: https://github.com/OCA/server-auth
Author: Antiun Ingeniería S.L., Tecnativa, Odoo Community Association (OCA)
Author-email: support@odoo-community.org
License: AGPL-3
Platform: UNKNOWN
Classifier: Programming Language :: Python
Classifier: Framework :: Odoo
Classifier: License :: OSI Approved :: GNU Affero General Public License v3
Requires-Python: >=2.7, !=3.0.*, !=3.1.*, !=3.2.*, !=3.3.*, !=3.4.*
Requires-Dist: email-validator
Requires-Dist: lxml
Requires-Dist: odoo (<11.1dev,>=11.0a)
